{
    "repliques": [
        {
            "flagsActives": [
            ],
            "flagsBloquants": [
            ],
            "flagsRequis": [
            ],
            "goAssocie": "",
            "id": "0",
            "repSuivantes": [
                "1",
                "2",
                "3"
            ],
            "texte": ""
        },
        {
            "flagsActives": [
                "140"
            ],
            "flagsBloquants": [
                "150",
                "140"
            ],
            "flagsRequis": [
                "130"
            ],
            "goAssocie": "TrezClubBD",
            "id": "1",
            "repSuivantes": [
            ],
            "texte": "Eh ! Viens par ici ! Saute par la fen\u00EAtre !"
        },
        {
            "flagsActives": [
            ],
            "flagsBloquants": [
            	"330"
            ],
            "flagsRequis": [
                "150"
            ],
            "goAssocie": "TrezClubBD",
            "id": "2",
            "repSuivantes": [
            ],
            "texte": "Je te souhaite la bienvenue au club BD !"
        },
        {
            "flagsActives": [
            ],
            "flagsBloquants": [
            	"350"
            ],
            "flagsRequis": [
                "330"
            ],
            "goAssocie": "TrezClubBD",
            "id": "3",
            "repSuivantes": [
            ],
            "texte": "Je me demande bien ce qu'il peut y avoir dans la foret pr\u00E8s des r\u00E9sidences..."
        },
        {
            "flagsActives": [
            ],
            "flagsBloquants": [
            ],
            "flagsRequis": [
                "350"
            ],
            "goAssocie": "TrezClubBD",
            "id": "3",
            "repSuivantes": [
            ],
            "texte": "N'oublie pas de te soigner avec de la Kroca Cola !"
        }
    ]
}
